[
  {
    "Title": "Chorinho Pra Ele",
    "Time_signature": "2/4",
    "Part": "A",
    "Key": "<music21.key.KeySignature of no sharps or flats>",
    "Generated": [
      "G5-0.25",
      "F#5-0.25",
      "E5-0.25",
      "D5-0.25",
      "C5-0.25",
      "B4-0.25",
      "A4-0.25",
      "G#4-0.25",
      "B4-0.25",
      "G#4-0.25",
      "A4-0.25",
      "B4-0.25",
      "C5-0.25",
      "D5-0.25",
      "E5-0.25",
      "G5-0.25",
      "G5-0.25",
      "F#5-0.25",
      "G5-0.25",
      "F#5-0.25",
      "G5-0.25",
      "G5-0.25",
      "G5-0.25",
      "A5-0.25",
      "A5-0.25",
      "A5-0.25",
      "G5-0.25",
      "A5-0.25",
      "G5-0.25",
      "A5-0.25",
      "G5-0.25",
      "A5-0.25",
      "G5-0.25",
      "D5-0.25",
      "E5-0.25",
      "G5-0.25",
      "A5-0.25",
      "A5-0.25",
      "G5-0.25",
      "D5-0.25",
      "A5-0.25",
      "A5-0.25",
      "G5-0.25",
      "F#5-0.25",
      "G5-0.25",
      "A5-0.25",
      "A5-0.25",
      "G5-0.25",
      "A5-0.25",
      "G5-0.25",
      "A5-0.25",
      "D6-0.25",
      "D5-0.25",
      "D5-0.25",
      "A5-0.25",
      "F5-0.25",
      "G5-0.25",
      "A5-0.25",
      "E5-0.25",
      "G5-0.25",
      "A5-0.25",
      "A5-0.25",
      "G5-0.25",
      "A5-0.25",
      "A5-0.25",
      "A5-0.25",
      "A5-0.25",
      "A5-0.25",
      "G5-0.25",
      "A5-0.25",
      "D5-0.25",
      "A5-0.25",
      "G5-0.25",
      "A5-0.25",
      "A5-0.25",
      "G5-0.25",
      "A5-0.25",
      "A5-0.25",
      "A5-0.25",
      "C5-0.25",
      "D5-0.25",
      "A5-0.25",
      "G5-0.25",
      "E5-0.25",
      "A5-0.5",
      "A5-0.25",
      "G5-0.25",
      "D5-0.25",
      "G5-0.25",
      "F#5-0.25",
      "A5-0.25",
      "G5-0.25",
      "A5-0.25",
      "G5-0.25",
      "A5-0.25",
      "G5-0.25",
      "A5-0.25",
      "D5-0.25",
      "A5-0.25",
      "A5-0.25",
      "A5-0.25",
      "E5-0.25",
      "A5-0.25",
      "G5-0.25",
      "A5-0.25",
      "A5-0.25",
      "G5-0.25",
      "A5-0.25",
      "B-5-0.25",
      "D5-0.25",
      "A5-0.25",
      "D5-0.25",
      "A5-0.25",
      "A5-0.25",
      "G5-0.25",
      "D6-0.25",
      "A5-0.25",
      "G5-0.25",
      "B-5-0.25",
      "A5-0.25",
      "G5-0.25",
      "D5-0.25",
      "A5-0.25",
      "A5-0.25",
      "G5-0.25",
      "F5-0.25",
      "A5-0.25",
      "G5-0.25",
      "D5-0.25",
      "G5-0.25",
      "A5-0.25",
      "G5-0.25",
      "A5-0.25",
      "G5-0.25",
      "A5-0.25",
      "B-5-0.25",
      "A5-0.25",
      "G5-0.25",
      "A5-0.25",
      "B-5-0.25",
      "A5-0.25",
      "G5-0.25",
      "A5-0.25"
    ],
    "Original": [
      "G5-0.25",
      "F#5-0.25",
      "E5-0.25",
      "D5-0.25",
      "C5-0.25",
      "B4-0.25",
      "A4-0.25",
      "G#4-0.25",
      "B4-0.25",
      "G#4-0.25",
      "A4-0.25",
      "B4-0.25",
      "C5-0.25",
      "D5-0.25",
      "E5-0.25",
      "G5-0.25",
      "F#5-0.25",
      "E5-0.25",
      "D5-0.25",
      "C5-0.25",
      "B4-0.25",
      "A4-0.25",
      "G4-0.25",
      "F#4-0.25",
      "A4-0.25",
      "G4-0.25",
      "F#4-0.25",
      "G4-0.25",
      "D5-0.25",
      "F#4-0.25",
      "G4-0.25",
      "A4-0.25",
      "B-4-0.25",
      "C5-0.25",
      "D-5-0.25",
      "E-5-0.25",
      "E5-0.25",
      "F#5-0.25",
      "G5-0.25",
      "A5-0.25",
      "B5-0.25",
      "G5-0.25",
      "E5-0.25",
      "F#5-0.25",
      "G5-0.25",
      "E5-0.25",
      "C5-0.25",
      "D5-0.25",
      "E5-0.25",
      "C5-0.25",
      "A4-0.25",
      "G4-0.25",
      "F#4-0.25",
      "E5-0.25",
      "D5-0.25",
      "C5-0.25",
      "B4-1.0",
      "rest-0.5",
      "D6-0.25",
      "F6-0.25",
      "C6-0.25",
      "E-6-0.25",
      "B-5-0.25",
      "D6-0.25",
      "A5-0.25",
      "C6-0.25",
      "G5-0.25",
      "B-5-0.25",
      "F5-0.25",
      "A5-0.25",
      "E-5-0.25",
      "G5-0.25",
      "D5-0.25",
      "F5-0.25",
      "C6-0.25",
      "E-6-0.25",
      "B-5-0.25",
      "D-6-0.25",
      "A-5-0.25",
      "C6-0.25",
      "G5-0.25",
      "B-5-0.25",
      "F5-0.25",
      "A-5-0.25",
      "G5-0.25",
      "F5-0.25",
      "E-5-0.25",
      "D-5-0.25",
      "C5-0.25",
      "B-4-0.25",
      "A-4-0.25",
      "G4-0.25",
      "A4-0.25",
      "B4-0.25",
      "D5-0.25",
      "G5-0.25",
      "F5-0.25",
      "E5-0.25",
      "B4-0.25",
      "D5-0.5",
      "C5-0.25",
      "C5-0.5",
      "E4-0.5",
      "E4-0.25",
      "F#4-0.25",
      "G#4-0.25",
      "B4-0.25",
      "E5-0.25",
      "D5-0.25",
      "C#5-0.25",
      "G#4-0.25",
      "B4-0.5",
      "A4-0.25",
      "rest-1.0",
      "F4-0.25",
      "G4-0.25",
      "A4-0.25",
      "C5-0.25",
      "B-4-0.25",
      "C5-0.25",
      "D5-0.25",
      "F5-0.25",
      "E-5-0.25",
      "F5-0.25",
      "G5-0.25",
      "B-5-0.25",
      "A-5-0.25",
      "B-5-0.25",
      "C6-0.25",
      "E-6-0.25",
      "D-6-0.25",
      "A-5-0.25",
      "F5-0.25",
      "D-5-0.25",
      "C5-0.25",
      "D5-0.25",
      "E5-0.25",
      "G5-0.25",
      "F5-0.5",
      "F5-0.25",
      "rest-0.25",
      "D5-0.25",
      "E5-0.25",
      "F#5-0.25"
    ],
    "Proba": [
      "1",
      "1",
      "1",
      "1",
      "1",
      "1",
      "1",
      "1",
      "1",
      "1",
      "1",
      "1",
      "1",
      "1",
      "1",
      "1",
      "0.16576542",
      "0.644775",
      "0.77981746",
      "0.59829736",
      "0.68667907",
      "0.16576542",
      "0.16576542",
      "0.6178619",
      "0.6178619",
      "0.6178619",
      "0.6315871",
      "0.6178619",
      "0.16576542",
      "0.6178619",
      "0.74269533",
      "0.6178619",
      "0.7039832",
      "0.047916397",
      "0.74013317",
      "0.15930165",
      "0.11009678",
      "0.6178619",
      "0.65306604",
      "0.1879148",
      "0.6178619",
      "0.6178619",
      "0.6998437",
      "0.76820487",
      "0.560503",
      "0.6178619",
      "0.6178619",
      "0.16576542",
      "0.6178619",
      "0.74483764",
      "0.6178619",
      "0.01010797",
      "0.36786947",
      "0.022247866",
      "0.6178619",
      "0.085703306",
      "0.7080691",
      "0.6178619",
      "0.5959477",
      "0.62489957",
      "0.6178619",
      "0.6178619",
      "0.7804138",
      "0.6178619",
      "0.6178619",
      "0.6178619",
      "0.6178619",
      "0.6178619",
      "0.74283326",
      "0.6881385",
      "0.05238626",
      "0.6178619",
      "0.76523995",
      "0.7136451",
      "0.6178619",
      "0.619917",
      "0.6178619",
      "0.6178619",
      "0.6178619",
      "0.08230749",
      "0.022247866",
      "0.7546726",
      "0.63360417",
      "0.017886981",
      "0.043995466",
      "0.6252437",
      "0.6521198",
      "0.022247866",
      "0.16576542",
      "0.018597806",
      "0.6178619",
      "0.6893065",
      "0.6119977",
      "0.16576542",
      "0.58178955",
      "0.6381616",
      "0.6178619",
      "0.022247866",
      "0.6178619",
      "0.6178619",
      "0.6178619",
      "0.14735669",
      "0.6178619",
      "0.5142996",
      "0.58297193",
      "0.6178619",
      "0.7703711",
      "0.6178619",
      "0.105334096",
      "0.022247866",
      "0.6178619",
      "0.022247866",
      "0.64291453",
      "0.6178619",
      "0.5987073",
      "0.01010797",
      "0.6178619",
      "0.7199513",
      "0.08281377",
      "0.72986573",
      "0.68148065",
      "0.14784633",
      "0.6178619",
      "0.6178619",
      "0.7349649",
      "0.085703306",
      "0.49798706",
      "0.16576542",
      "0.3589041",
      "0.4407113",
      "0.6178619",
      "0.762955",
      "0.5898879",
      "0.3998159",
      "0.60425764",
      "0.020069767",
      "0.6178619",
      "0.75798494",
      "0.62972087",
      "0.042386",
      "0.7463186",
      "0.66513675",
      "0.6178619"
    ]
  },
  {
    "Title": "AMAPA",
    "Time_signature": "2/4",
    "Part": "A",
    "Key": "C major",
    "Generated": [
      "rest-0.25",
      "E4-0.5",
      "E4-0.25",
      "E4-0.25",
      "G4-0.5",
      "F4-0.25",
      "E4-1.0",
      "B4-1.0",
      "rest-0.25",
      "rest-0.25",
      "E4-0.25",
      "rest-0.25",
      "rest-0.25",
      "rest-0.25",
      "rest-0.25",
      "rest-0.25",
      "rest-0.25",
      "F4-1.0",
      "rest-0.25",
      "rest-0.25",
      "E4-0.25",
      "rest-0.25",
      "rest-0.25",
      "rest-0.25",
      "E4-0.5",
      "A4-0.25",
      "rest-0.25",
      "F4-0.25",
      "G4-0.5",
      "rest-0.25",
      "E4-0.5",
      "rest-0.25",
      "rest-0.25",
      "D#4-0.25",
      "rest-0.25",
      "E4-0.25",
      "rest-0.25",
      "rest-0.25",
      "E4-0.5",
      "rest-0.25",
      "E4-0.5",
      "rest-0.25",
      "A3-0.25",
      "rest-0.25",
      "rest-0.25",
      "rest-0.25",
      "E4-0.25",
      "rest-0.25",
      "rest-0.25",
      "rest-0.25",
      "E4-0.25",
      "rest-0.25",
      "rest-0.25",
      "G4-0.5",
      "rest-0.25",
      "E4-0.5",
      "rest-0.25",
      "rest-0.25",
      "rest-0.25",
      "rest-0.25",
      "E4-0.25",
      "rest-0.25",
      "E4-0.5",
      "rest-0.25",
      "E4-0.5",
      "rest-0.25",
      "E4-0.25",
      "rest-0.25",
      "F#4-0.25",
      "E4-0.25",
      "rest-0.25",
      "rest-0.25",
      "rest-0.25",
      "rest-0.25",
      "F#4-1.0",
      "rest-0.25",
      "A4-0.25",
      "E4-0.25",
      "rest-0.25",
      "G4-0.5",
      "rest-0.25",
      "rest-0.25",
      "E4-0.5",
      "rest-0.25",
      "rest-0.25",
      "E4-0.25",
      "rest-0.25",
      "rest-0.25",
      "rest-0.25",
      "rest-0.25",
      "E4-0.25",
      "rest-0.25",
      "E4-0.25",
      "D5-1.0",
      "rest-0.25",
      "E4-0.5",
      "rest-0.25",
      "E4-0.5",
      "rest-0.25",
      "E4-0.5",
      "F#4-0.25",
      "rest-0.25",
      "E4-0.25",
      "G4-0.5",
      "rest-0.25",
      "E4-0.5",
      "rest-0.25",
      "rest-0.25",
      "rest-0.25",
      "G4-0.25",
      "rest-0.25"
    ],
    "Original": [
      "rest-0.25",
      "E4-0.5",
      "E4-0.25",
      "E4-0.25",
      "G4-0.5",
      "F4-0.25",
      "E4-1.0",
      "B4-1.0",
      "rest-0.25",
      "E4-0.5",
      "E4-0.25",
      "E4-0.25",
      "G4-0.5",
      "F4-0.25",
      "E4-1.0",
      "B4-1.0",
      "rest-0.25",
      "E5-0.5",
      "E5-0.25",
      "E5-0.25",
      "D#5-0.5",
      "E5-0.25",
      "F5-0.5",
      "D5-0.5",
      "B4-0.5",
      "G#4-0.5",
      "A4-0.5",
      "A4-0.5",
      "G4-0.5",
      "F4-0.5",
      "F4-1.0",
      "E4-1.0"
    ],
    "Proba": [
      "1",
      "1",
      "1",
      "1",
      "1",
      "1",
      "1",
      "1",
      "0.8393652",
      "0.8403873",
      "0.6453254",
      "0.8403873",
      "0.8403873",
      "0.8403873",
      "0.8403873",
      "0.8403873",
      "0.8403873",
      "0.016228333",
      "0.8248317",
      "0.8403873",
      "0.7837258",
      "0.8403873",
      "0.8403873",
      "0.8403873",
      "0.7809669",
      "0.015012193",
      "0.8403873",
      "0.020487072",
      "0.122299545",
      "0.65248835",
      "0.6187949",
      "0.8364996",
      "0.8403873",
      "0.032283224",
      "0.8403873",
      "0.012417914",
      "0.8403873",
      "0.8403873",
      "0.6241459",
      "0.8523988",
      "0.7541307",
      "0.8403873",
      "0.018919667",
      "0.7867966",
      "0.8403873",
      "0.8403873",
      "0.7769688",
      "0.7490801",
      "0.8403873",
      "0.8403873",
      "0.03308782",
      "0.8403873",
      "0.8403873",
      "0.07150841",
      "0.84984124",
      "0.820593",
      "0.8397968",
      "0.8403873",
      "0.8403873",
      "0.8403873",
      "0.51239824",
      "0.7126354",
      "0.68067646",
      "0.82613605",
      "0.75841206",
      "0.8990205",
      "0.16729169",
      "0.8403873",
      "0.016151737",
      "0.05233553",
      "0.8403873",
      "0.8403873",
      "0.8403873",
      "0.8403873",
      "0.015168466",
      "0.8403873",
      "0.015012193",
      "0.7813818",
      "0.83325905",
      "0.66095906",
      "0.85874134",
      "0.8403873",
      "0.7931945",
      "0.9008485",
      "0.8403873",
      "0.012417914",
      "0.8403873",
      "0.8403873",
      "0.8403873",
      "0.8403873",
      "0.716838",
      "0.82404137",
      "0.6215151",
      "0.012769715",
      "0.8403873",
      "0.66066426",
      "0.81839794",
      "0.69462293",
      "0.8403873",
      "0.74635047",
      "0.04949816",
      "0.8403873",
      "0.792354",
      "0.6085202",
      "0.8142008",
      "0.7148447",
      "0.8403873",
      "0.8403873",
      "0.8403873",
      "0.016339608",
      "0.8403873"
    ]
  },
  {
    "Title": "JORGE DO FUSA",
    "Time_signature": "2/4",
    "Part": "A",
    "Key": "D major",
    "Generated": [
      "F#3-0.25",
      "C#5-0.25",
      "C#5-0.25",
      "B4-0.25",
      "C#5-1.0",
      "rest-0.25",
      "F#5-0.25",
      "F#5-0.25",
      "E5-0.25",
      "A5-0.5",
      "A#5-0.25",
      "rest-0.25",
      "F#3-0.25",
      "rest-0.25",
      "D5-0.25",
      "rest-0.25",
      "F#3-0.25",
      "rest-0.25",
      "G3-0.25",
      "G#3-0.25",
      "C5-2.0",
      "rest-0.25",
      "E5-0.25",
      "F#3-0.25",
      "C#5-0.25",
      "F#3-0.25",
      "C#5-0.25",
      "rest-0.25",
      "F#3-0.25",
      "G3-0.25",
      "F3-0.5",
      "F3-0.25",
      "D3-0.25",
      "E5-0.25",
      "G3-0.25",
      "F#3-0.5",
      "E5-0.25",
      "C6-2.0",
      "C6-0.5",
      "rest-0.25",
      "rest-0.25",
      "E3-0.25",
      "rest-0.25",
      "rest-0.25",
      "E5-0.25",
      "E5-0.25",
      "C6-2.0",
      "A#4-1.0",
      "rest-0.25",
      "A#6-0.25",
      "D#6-0.25",
      "rest-0.25",
      "C5-0.25",
      "G7-1.0",
      "rest-0.25",
      "rest-1.0",
      "E5-0.25",
      "C6-2.0",
      "C#5-0.25",
      "C#5-1.0",
      "rest-1.0",
      "rest-0.25",
      "rest-0.25",
      "rest-0.25",
      "A#6-0.25",
      "B6-0.25",
      "C#5-0.25",
      "D#5-2.0",
      "rest-0.25",
      "B#4-0.25",
      "rest-0.25",
      "E5-0.25",
      "E5-0.25",
      "F3-0.25",
      "B#4-0.25",
      "rest-0.25",
      "E5-0.25",
      "rest-0.25",
      "B#4-0.25",
      "rest-0.25",
      "A#6-0.25",
      "B6-0.25",
      "rest-0.25",
      "B#4-0.25",
      "C#5-0.25",
      "E7-0.5"
    ],
    "Original": [
      "F#3-0.25",
      "C#5-0.25",
      "C#5-0.25",
      "B4-0.25",
      "C#5-1.0",
      "rest-0.25",
      "F#5-0.25",
      "F#5-0.25",
      "E5-0.25",
      "A5-0.5",
      "A#5-0.25",
      "B5-0.25",
      "A5-0.25",
      "B5-0.25",
      "A5-0.25",
      "B5-0.25",
      "B-5-0.25",
      "A5-0.25",
      "A-5-0.25",
      "G5-1.0",
      "F#5-1.0",
      "rest-0.25",
      "A5-0.5",
      "G5-0.25",
      "F#5-0.25",
      "B4-0.25",
      "A#4-0.25",
      "C#5-0.25",
      "E5-0.25",
      "F#4-0.25",
      "A4-0.25",
      "D5-0.25",
      "C#5-0.25",
      "D5-0.25",
      "F#5-0.25",
      "A5-0.25",
      "C#6-0.5",
      "B5-0.25",
      "rest-0.25",
      "A#5-0.25",
      "B5-0.25",
      "C6-0.25",
      "C#6-0.125",
      "B5-0.125",
      "A5-0.125",
      "G5-0.125",
      "F5-0.125",
      "D#5-0.125",
      "C#5-0.125",
      "B4-0.125",
      "A4-0.125",
      "G4-0.125",
      "F4-0.125",
      "D#4-0.125",
      "C#4-0.125",
      "B3-0.125",
      "A3-0.125",
      "G3-0.125",
      "F#3-0.25",
      "C#5-0.25",
      "C#5-0.25",
      "B4-0.25",
      "C#5-1.0",
      "rest-0.25",
      "F#5-0.25",
      "F#5-0.25",
      "E5-0.25",
      "A5-0.5",
      "A#5-0.25",
      "B5-0.25",
      "A5-0.25",
      "B5-0.25",
      "A5-0.25",
      "B5-0.25",
      "B-5-0.25",
      "A5-0.25",
      "A-5-0.25",
      "G5-0.5",
      "G5-0.25",
      "E5-0.25",
      "C5-0.25",
      "B4-0.25",
      "F#5-0.5",
      "rest-0.25",
      "A5-0.5",
      "G5-0.25",
      "F#5-0.5",
      "E5-0.25",
      "C#5-0.25",
      "D5-0.25",
      "F#5-0.25",
      "A5-0.25",
      "C#6-0.5",
      "B5-0.25",
      "A5-0.25",
      "B4-0.25",
      "D5-0.25",
      "G5-0.25",
      "E-5-0.5",
      "F#5-0.25",
      "E5-0.25",
      "E5-0.25",
      "E5-0.25",
      "E5-0.25",
      "E5-1.0"
    ],
    "Proba": [
      "1",
      "1",
      "1",
      "1",
      "1",
      "1",
      "1",
      "1",
      "1",
      "1",
      "1",
      "0.64085656",
      "0.6774078",
      "0.64085656",
      "0.019655474",
      "0.6903103",
      "0.18442829",
      "0.64085656",
      "0.07599708",
      "0.60454255",
      "0.19592835",
      "0.64085656",
      "0.19253807",
      "0.2852929",
      "0.8235454",
      "0.62664664",
      "0.857026",
      "0.64085656",
      "0.46167266",
      "0.5776706",
      "0.30709705",
      "0.70222926",
      "0.6260423",
      "0.19253807",
      "0.6098263",
      "0.41873527",
      "0.19253807",
      "0.10540959",
      "0.62138677",
      "0.64085656",
      "0.64085656",
      "0.047345616",
      "0.64085656",
      "0.64085656",
      "0.19253807",
      "0.19253807",
      "0.6562315",
      "0.12511285",
      "0.85272336",
      "0.42547524",
      "0.0443358",
      "0.64085656",
      "0.031749062",
      "0.036032308",
      "0.64085656",
      "0.024198886",
      "0.08039937",
      "0.29738605",
      "0.045121722",
      "0.52765095",
      "0.060679324",
      "0.8133779",
      "0.64085656",
      "0.64085656",
      "0.7763884",
      "0.74478066",
      "0.045121722",
      "0.025911512",
      "0.64085656",
      "0.37441525",
      "0.64085656",
      "0.19253807",
      "0.19253807",
      "0.18740061",
      "0.011554115",
      "0.64085656",
      "0.19253807",
      "0.64085656",
      "0.51290554",
      "0.64085656",
      "0.6334761",
      "0.8293541",
      "0.64085656",
      "0.29744998",
      "0.8181351",
      "0.14223032"
    ]
  },
  {
    "Title": "KARAT\u00ca",
    "Time_signature": "2/4",
    "Part": "A",
    "Key": "F major",
    "Generated": [
      "F4-0.5",
      "E4-0.25",
      "F4-0.25",
      "G4-0.25",
      "A4-0.5",
      "A4-0.5",
      "B-4-0.5",
      "C5-0.5",
      "A4-0.5",
      "G4-0.5",
      "F4-0.25",
      "F4-0.5",
      "G4-0.5",
      "F4-0.25",
      "A4-0.5",
      "F4-0.25",
      "B-4-0.25",
      "F4-0.25",
      "G4-0.5",
      "F4-0.25",
      "A4-0.5",
      "G4-0.5",
      "G4-0.5",
      "F4-0.25",
      "E4-0.25",
      "F4-0.25",
      "E4-0.25",
      "A4-0.5",
      "G4-0.5",
      "G4-0.5",
      "G4-0.5",
      "G4-0.5",
      "E4-0.25",
      "E-4-0.5",
      "G4-0.5",
      "F4-0.25",
      "A4-0.5",
      "F4-0.25",
      "D5-0.5",
      "F4-0.5",
      "G4-0.5",
      "F4-0.5",
      "G4-0.5",
      "F4-0.25",
      "E4-0.25",
      "A4-0.5",
      "G4-0.5",
      "G4-0.5",
      "F4-0.5",
      "G4-0.5",
      "E4-0.25",
      "G4-0.5",
      "G4-0.5",
      "G4-0.5",
      "F4-0.25",
      "G4-0.5",
      "G4-0.5",
      "E4-0.25",
      "F4-0.25",
      "G4-0.5",
      "F4-0.25",
      "A4-0.5",
      "F4-0.5",
      "G4-0.5",
      "F4-0.5",
      "G4-0.5",
      "F4-0.25",
      "F4-0.5",
      "G4-0.5",
      "A4-0.25",
      "G4-0.5",
      "G4-0.5",
      "G4-0.5",
      "G4-0.5",
      "E4-0.25",
      "G4-0.5",
      "F4-0.25",
      "G4-0.5",
      "G4-0.5",
      "G4-0.5",
      "A4-0.5",
      "G4-0.5",
      "F4-0.5",
      "D5-0.5",
      "G4-0.5",
      "A4-0.25"
    ],
    "Original": [
      "F4-0.5",
      "E4-0.25",
      "F4-0.25",
      "G4-0.25",
      "A4-0.5",
      "A4-0.5",
      "B-4-0.5",
      "C5-0.5",
      "A4-0.5",
      "B-4-0.25",
      "A4-0.25",
      "G4-0.25",
      "F4-0.25",
      "E4-0.25",
      "D4-0.25",
      "C4-0.5",
      "C4-0.5",
      "C5-1.0",
      "A4-0.5",
      "B-4-0.25",
      "A4-0.25",
      "G4-0.25",
      "F4-0.25",
      "E4-0.25",
      "D4-0.25",
      "C4-0.5",
      "C4-0.5",
      "E4-0.5",
      "G4-0.5",
      "C5-0.5",
      "B-4-0.5",
      "A4-0.5",
      "G#4-0.25",
      "B-4-0.25",
      "A4-0.5",
      "A4-0.5",
      "F4-0.5",
      "E4-0.5",
      "F4-0.5",
      "G4-0.5",
      "F4-0.5",
      "E4-0.5",
      "F4-0.5",
      "A4-0.5",
      "C5-0.5",
      "F5-0.5",
      "C#5-0.5",
      "E5-0.5",
      "D5-0.5",
      "C#5-0.25",
      "E5-0.25",
      "D5-0.5",
      "D5-0.5",
      "B-4-0.5",
      "A4-0.5",
      "G4-0.5",
      "A4-0.5",
      "C5-0.5",
      "F4-0.5",
      "A4-0.5",
      "G4-0.5",
      "B-4-0.5",
      "E4-0.5",
      "G4-0.5",
      "F4-0.5",
      "A4-0.25",
      "C5-0.5",
      "C4-0.5",
      "C4-0.5",
      "C4-0.5",
      "D4-0.5",
      "E4-0.5"
    ],
    "Proba": [
      "1",
      "1",
      "1",
      "1",
      "1",
      "1",
      "1",
      "1",
      "1",
      "0.6774231",
      "0.70502585",
      "0.5326259",
      "0.6774231",
      "0.63716567",
      "0.13240609",
      "0.8366979",
      "0.0154360235",
      "0.45030725",
      "0.6774231",
      "0.8554955",
      "0.4749958",
      "0.6774231",
      "0.6774231",
      "0.83146304",
      "0.7441809",
      "0.722992",
      "0.73484933",
      "0.13240609",
      "0.6774231",
      "0.6774231",
      "0.6774231",
      "0.6774231",
      "0.626958",
      "0.0255712",
      "0.5873408",
      "0.7110847",
      "0.7781114",
      "0.79121447",
      "0.018694336",
      "0.057481706",
      "0.6774231",
      "0.030486124",
      "0.6774231",
      "0.6532331",
      "0.78151065",
      "0.13240609",
      "0.6774231",
      "0.6774231",
      "0.057481706",
      "0.6774231",
      "0.60513985",
      "0.6774231",
      "0.6774231",
      "0.6774231",
      "0.7847543",
      "0.6774231",
      "0.6774231",
      "0.70821095",
      "0.64190036",
      "0.6504841",
      "0.7095716",
      "0.757458",
      "0.057481706",
      "0.6700068",
      "0.5307231",
      "0.74690485",
      "0.8086807",
      "0.057481706",
      "0.6774231",
      "0.02127519",
      "0.6774231",
      "0.6774231",
      "0.6774231",
      "0.6774231",
      "0.24010034",
      "0.6774231",
      "0.7739935",
      "0.7427655",
      "0.6774231",
      "0.6774231",
      "0.13240609",
      "0.6774231",
      "0.44242308",
      "0.018694336",
      "0.6774231",
      "0.13240609"
    ]
  },
  {
    "Title": "Receita de Samba",
    "Time_signature": "2/4",
    "Part": "A",
    "Key": "G major",
    "Generated": [
      "rest-0.25",
      "D5-0.25",
      "B4-0.25",
      "A4-0.25",
      "G4-0.25",
      "A4-0.25",
      "B4-0.25",
      "D5-0.25",
      "D5-0.25",
      "B4-0.5",
      "A4-0.25",
      "G4-0.25",
      "A4-0.25",
      "B4-0.25",
      "E-4-0.25",
      "G4-0.25",
      "rest-0.25",
      "B4-0.25",
      "D5-0.25",
      "rest-0.25",
      "rest-0.25",
      "rest-0.25",
      "rest-0.25",
      "B4-0.25",
      "A4-0.5",
      "D5-0.25",
      "rest-0.25",
      "rest-0.25",
      "rest-0.25",
      "A4-0.5",
      "B4-0.25",
      "D5-0.25",
      "rest-0.25",
      "D5-0.25",
      "C5-2.0",
      "rest-0.25",
      "rest-0.25",
      "rest-0.25",
      "rest-0.25",
      "A4-0.5",
      "D5-0.25",
      "rest-0.25",
      "G4-0.25",
      "rest-0.25",
      "rest-0.25",
      "B4-0.25",
      "rest-0.25",
      "rest-0.25",
      "B4-0.25",
      "rest-0.25",
      "D5-0.25",
      "B4-1.0",
      "rest-0.25",
      "G#3-0.25",
      "B4-0.25",
      "rest-0.25",
      "D5-0.25",
      "E5-0.25",
      "rest-0.25",
      "rest-0.25",
      "rest-0.25",
      "A4-0.5",
      "rest-0.25",
      "rest-0.25",
      "rest-0.25",
      "rest-0.25",
      "rest-0.25",
      "rest-0.25",
      "rest-0.25",
      "rest-0.25",
      "rest-0.25",
      "G4-0.25",
      "B-4-0.25",
      "B4-0.25",
      "rest-0.25",
      "D5-0.25",
      "rest-0.25",
      "rest-0.25",
      "rest-0.25",
      "rest-0.25",
      "A4-0.25",
      "B4-0.25",
      "D5-0.25",
      "rest-0.25",
      "D5-0.25",
      "rest-0.25",
      "F#4-0.25",
      "rest-0.25",
      "D5-0.25",
      "rest-0.25",
      "rest-0.25",
      "A4-0.25",
      "rest-0.25",
      "rest-0.25",
      "D5-0.25",
      "rest-0.25",
      "rest-0.25",
      "rest-0.25",
      "D5-0.25",
      "rest-0.25",
      "D5-0.25",
      "B4-1.0",
      "rest-0.25",
      "rest-0.25",
      "rest-0.25",
      "B4-0.25",
      "D5-0.25",
      "B4-1.0",
      "rest-0.25",
      "rest-0.25",
      "A4-0.5",
      "D5-0.25",
      "rest-0.25",
      "D5-0.25",
      "rest-0.25",
      "D5-0.25",
      "A4-0.25",
      "rest-0.25",
      "D5-0.25",
      "rest-0.25",
      "rest-0.25",
      "D5-0.25"
    ],
    "Original": [
      "rest-0.25",
      "D5-0.25",
      "B4-0.25",
      "A4-0.25",
      "G4-0.25",
      "A4-0.25",
      "B4-0.25",
      "D5-0.25",
      "D5-0.25",
      "B4-0.5",
      "A4-0.25",
      "G4-0.25",
      "A4-0.25",
      "B4-0.25",
      "E-4-0.25",
      "E-4-1.0",
      "E-4-0.25",
      "B4-0.5",
      "A4-0.25",
      "A4-2.0",
      "rest-0.25",
      "D5-0.25",
      "B4-0.25",
      "A4-0.25",
      "G4-0.25",
      "A4-0.25",
      "B4-0.25",
      "D5-0.25",
      "D5-0.25",
      "B4-0.5",
      "A4-0.25",
      "G4-0.25",
      "A4-0.25",
      "B4-0.25",
      "E-4-0.25",
      "E-4-1.0",
      "E-4-0.25",
      "B4-0.5",
      "A4-0.25",
      "A4-2.0",
      "rest-0.25",
      "G4-0.25",
      "A4-0.25",
      "A#4-0.25",
      "B4-0.25",
      "D5-0.25",
      "B4-0.25",
      "A4-0.25",
      "A4-0.5",
      "G4-0.25",
      "G4-1.0",
      "rest-0.25",
      "G4-0.25",
      "A4-0.25",
      "A#4-0.25",
      "B4-0.25",
      "E5-0.25",
      "B4-0.25",
      "A4-0.25",
      "A4-0.5",
      "G4-0.25",
      "G4-1.0",
      "rest-0.25",
      "A4-0.25",
      "B4-0.25",
      "B#4-0.25",
      "C#5-0.25",
      "E5-0.25",
      "C#5-0.25",
      "B4-0.25",
      "B4-0.25",
      "A4-0.5",
      "B4-0.25",
      "C#5-0.25",
      "B4-0.25",
      "A4-0.25",
      "C5-0.25",
      "C5-1.0",
      "rest-0.25",
      "D5-0.25",
      "C5-0.25",
      "B4-0.25",
      "B-4-0.25",
      "D5-0.5",
      "D4-0.25",
      "D4-1.0",
      "rest-0.25",
      "D5-0.25",
      "B4-0.25",
      "A4-0.25",
      "G4-0.25",
      "A4-0.25",
      "B4-0.25",
      "D5-0.25",
      "D5-0.25",
      "B4-0.5",
      "A4-0.25",
      "G4-0.25",
      "A4-0.25",
      "B4-0.25",
      "E-4-0.25",
      "E-4-1.0",
      "E-4-0.25",
      "B4-0.5",
      "A4-0.25",
      "A4-2.0",
      "rest-0.25",
      "D5-0.25",
      "B4-0.25",
      "A4-0.25",
      "G4-0.25",
      "A4-0.25",
      "B4-0.25",
      "D5-0.25",
      "D5-0.25",
      "A4-0.25",
      "G4-0.25",
      "D#5-0.25",
      "D#5-0.25",
      "A4-0.25",
      "G4-0.25",
      "E5-0.25",
      "E5-2.0",
      "E5-2.0",
      "rest-0.25",
      "E5-0.5",
      "E5-0.25",
      "E5-0.25",
      "D#5-0.25",
      "E5-0.25",
      "F#5-0.25",
      "F#5-0.5",
      "E5-0.25",
      "E5-1.0",
      "rest-0.25",
      "D5-0.5",
      "D5-0.25",
      "D5-0.25",
      "C#5-0.25",
      "D5-0.25",
      "E5-0.25",
      "E5-0.5",
      "D5-0.25",
      "D5-1.0",
      "rest-0.25",
      "C5-0.5",
      "C5-0.25",
      "C5-0.25",
      "D#4-0.25",
      "E4-0.25",
      "B4-0.25",
      "B4-0.5",
      "D5-0.25",
      "D5-0.25",
      "B4-0.25",
      "D4-0.25",
      "G4-0.25",
      "G4-2.0",
      "rest-2.0"
    ],
    "Proba": [
      "1",
      "1",
      "1",
      "1",
      "1",
      "1",
      "1",
      "1",
      "1",
      "1",
      "1",
      "1",
      "1",
      "1",
      "1",
      "0.5790674",
      "0.8193882",
      "0.2570986",
      "0.73370177",
      "0.057408333",
      "0.8193882",
      "0.8193882",
      "0.8193882",
      "0.6003458",
      "0.027582122",
      "0.46009275",
      "0.8193882",
      "0.8193882",
      "0.8193882",
      "0.6113136",
      "0.27725694",
      "0.817763",
      "0.8193882",
      "0.776976",
      "0.014373031",
      "0.82523644",
      "0.8193882",
      "0.8193882",
      "0.8193882",
      "0.029641282",
      "0.45578",
      "0.8193882",
      "0.015980832",
      "0.8193882",
      "0.8193882",
      "0.7295049",
      "0.8193882",
      "0.8193882",
      "0.594954",
      "0.8193882",
      "0.8313948",
      "0.025229033",
      "0.86516887",
      "0.02107335",
      "0.82640505",
      "0.8193882",
      "0.8544295",
      "0.013428108",
      "0.8193882",
      "0.8193882",
      "0.8193882",
      "0.529658",
      "0.8193882",
      "0.8193882",
      "0.8193882",
      "0.8193882",
      "0.8193882",
      "0.8193882",
      "0.8193882",
      "0.8193882",
      "0.8193882",
      "0.033683103",
      "0.026533704",
      "0.57804114",
      "0.8193882",
      "0.84700555",
      "0.8193882",
      "0.8193882",
      "0.8193882",
      "0.8193882",
      "0.1551403",
      "0.7156999",
      "0.7820087",
      "0.79917324",
      "0.60961",
      "0.8193882",
      "0.016359828",
      "0.8193882",
      "0.803147",
      "0.81713825",
      "0.8193882",
      "0.08221063",
      "0.8193882",
      "0.8193882",
      "0.76518303",
      "0.8193882",
      "0.8193882",
      "0.8193882",
      "0.72133416",
      "0.8193882",
      "0.84325933",
      "0.033751555",
      "0.8193882",
      "0.8193882",
      "0.8193882",
      "0.6659582",
      "0.81728435",
      "0.12983169",
      "0.6632768",
      "0.8193882",
      "0.025312405",
      "0.6893152",
      "0.8193882",
      "0.8290392",
      "0.8193882",
      "0.74889934",
      "0.013183995",
      "0.8193882",
      "0.8384753",
      "0.79177004",
      "0.8193882",
      "0.6644129"
    ]
  },
  {
    "Title": "Lingua de Preto",
    "Time_signature": "2/4",
    "Part": "A",
    "Key": "C major",
    "Generated": [
      "rest-0.25",
      "F4-0.25",
      "F5-0.25",
      "D4-0.25",
      "D5-0.25",
      "B3-0.25",
      "B4-0.25",
      "G3-0.25",
      "rest-0.25",
      "E4-0.25",
      "E5-0.25",
      "C4-0.25",
      "C5-0.25",
      "A3-0.25",
      "A4-0.25",
      "F3-0.25",
      "B3-0.25",
      "G3-0.25",
      "G#3-0.25",
      "A3-0.25",
      "G3-0.25",
      "D5-0.25",
      "B3-0.25",
      "D5-0.25",
      "rest-0.25",
      "F5-0.25",
      "B3-0.25",
      "B3-0.25",
      "D4-0.5",
      "B3-0.25",
      "G3-0.25",
      "B3-0.25",
      "F5-0.25",
      "B3-0.25",
      "G3-0.25",
      "D4-0.5",
      "B3-0.25",
      "G3-0.25",
      "B3-0.25",
      "B3-0.25",
      "D5-0.25",
      "B3-0.25",
      "B3-0.25",
      "G#3-0.25",
      "B3-0.25",
      "B3-0.25",
      "G#3-0.25",
      "G3-0.25",
      "G#3-0.25",
      "B3-0.25",
      "G#3-0.25",
      "G3-0.25",
      "B3-0.25",
      "G3-0.25",
      "G#3-0.25",
      "B3-0.25",
      "G3-0.25",
      "D5-0.25",
      "rest-0.5",
      "G3-0.25",
      "D5-0.25",
      "B3-0.25",
      "G3-0.25",
      "G#3-0.25",
      "B3-0.25",
      "G3-0.25",
      "G#3-0.25",
      "G3-0.25",
      "G3-0.25",
      "G#3-0.25",
      "D5-0.25",
      "B3-0.25",
      "D4-0.5",
      "G3-0.25",
      "G#3-0.25",
      "B3-0.25",
      "F5-0.25",
      "B3-0.25",
      "D4-0.25",
      "B3-0.25",
      "G#3-0.25",
      "B3-0.25",
      "G3-0.25",
      "G#3-0.25",
      "G3-0.25",
      "G#3-0.25",
      "B3-0.25",
      "G#3-0.25",
      "G3-0.25",
      "G#3-0.25",
      "D5-0.25",
      "B3-0.25",
      "G3-0.25",
      "G#3-0.25",
      "G3-0.25",
      "G#3-0.25",
      "B3-0.25",
      "B3-0.25",
      "G#3-0.25",
      "B3-0.25",
      "B3-0.25",
      "F5-0.25",
      "G3-0.25",
      "G#3-0.25",
      "B3-0.25",
      "G3-0.25",
      "G#3-0.25",
      "B3-0.25",
      "F5-0.25",
      "G3-0.25",
      "G#3-0.25",
      "G3-0.25",
      "G3-0.25",
      "G3-0.25",
      "G#3-0.25",
      "B3-0.25",
      "G#3-0.25",
      "G3-0.25",
      "G3-0.25",
      "G#3-0.25",
      "B3-0.25",
      "G#3-0.25",
      "B3-0.25",
      "G#3-0.25",
      "B3-0.25",
      "B3-0.25",
      "E-4-0.5",
      "G3-0.25",
      "B3-0.25",
      "G#3-0.25",
      "G3-0.25",
      "D5-0.25",
      "B3-0.25",
      "F5-0.25",
      "B3-0.25",
      "G3-0.25",
      "G3-0.25",
      "G3-0.25",
      "G3-0.25"
    ],
    "Original": [
      "rest-0.25",
      "F4-0.25",
      "F5-0.25",
      "D4-0.25",
      "D5-0.25",
      "B3-0.25",
      "B4-0.25",
      "G3-0.25",
      "rest-0.25",
      "E4-0.25",
      "E5-0.25",
      "C4-0.25",
      "C5-0.25",
      "A3-0.25",
      "A4-0.25",
      "F3-0.25",
      "rest-0.25",
      "D4-0.25",
      "D5-0.25",
      "B3-0.25",
      "B4-0.25",
      "G3-0.25",
      "G4-0.25",
      "E3-0.25",
      "rest-0.25",
      "G4-0.25",
      "G5-0.25",
      "E4-0.25",
      "E5-0.25",
      "C4-0.25",
      "C5-0.25",
      "A3-0.25",
      "A4-0.25",
      "F4-0.25",
      "F5-0.25",
      "D4-0.25",
      "D5-0.25",
      "B3-0.25",
      "B4-0.25",
      "G3-0.25",
      "G4-0.25",
      "rest-0.25",
      "E5-0.5",
      "D5-0.25",
      "C5-0.5",
      "B4-0.25",
      "B4-0.25",
      "C5-0.25",
      "C#5-0.25",
      "D5-0.25",
      "D#5-0.25",
      "E5-0.25",
      "F5-0.125",
      "F#5-0.125",
      "G5-0.25",
      "rest-0.25",
      "G4-0.25",
      "G5-0.25",
      "E4-0.25",
      "E5-0.25",
      "C4-0.25",
      "C5-0.25",
      "A3-0.25",
      "rest-0.25",
      "F4-0.25",
      "F5-0.25",
      "D4-0.25",
      "D5-0.25",
      "B3-0.25",
      "B4-0.25",
      "G3-0.25",
      "rest-0.25",
      "E4-0.25",
      "E5-0.25",
      "C4-0.25",
      "C5-0.25",
      "A3-0.25",
      "A4-0.25",
      "F3-0.25",
      "rest-0.25",
      "D4-0.25",
      "D5-0.25",
      "B3-0.25",
      "B4-0.25",
      "G3-0.25",
      "G4-0.25",
      "E3-0.25",
      "rest-0.25",
      "G4-0.25",
      "G5-0.25",
      "E4-0.25",
      "E5-0.25",
      "C4-0.25",
      "C5-0.25",
      "A3-0.25",
      "A4-0.25",
      "F4-0.25",
      "F5-0.25",
      "D4-0.25",
      "D5-0.25",
      "B3-0.25",
      "B4-0.25",
      "G3-0.25",
      "G4-0.25",
      "rest-0.25",
      "E5-0.5",
      "D5-0.25",
      "C5-0.5",
      "A5-0.25",
      "A5-0.25",
      "G5-0.25",
      "F5-0.25",
      "D5-0.25",
      "B4-0.25",
      "G4-0.25",
      "F4-0.25",
      "D4-0.25",
      "C4-0.25",
      "G4-0.25",
      "G5-0.25",
      "E4-0.25",
      "E5-0.25",
      "C4-0.25",
      "C5-0.25",
      "A3-0.25"
    ],
    "Proba": [
      "1",
      "1",
      "1",
      "1",
      "1",
      "1",
      "1",
      "1",
      "1",
      "1",
      "1",
      "1",
      "1",
      "1",
      "1",
      "1",
      "0.4773472",
      "0.47668162",
      "0.23605122",
      "0.6387935",
      "0.62051666",
      "0.14751495",
      "0.26620847",
      "0.14751495",
      "0.6729032",
      "0.74030775",
      "0.564848",
      "0.26620847",
      "0.060342595",
      "0.802756",
      "0.47668162",
      "0.26620847",
      "0.81413543",
      "0.787073",
      "0.47668162",
      "0.6582763",
      "0.26620847",
      "0.47668162",
      "0.26620847",
      "0.26620847",
      "0.14751495",
      "0.8148196",
      "0.26620847",
      "0.020890059",
      "0.8421316",
      "0.26620847",
      "0.020890059",
      "0.47668162",
      "0.57434916",
      "0.8279812",
      "0.67305833",
      "0.47668162",
      "0.26620847",
      "0.47668162",
      "0.7532389",
      "0.8622778",
      "0.47668162",
      "0.14751495",
      "0.017901001",
      "0.47668162",
      "0.14751495",
      "0.77299523",
      "0.47668162",
      "0.7848214",
      "0.82854116",
      "0.47668162",
      "0.73600596",
      "0.47668162",
      "0.47668162",
      "0.70976776",
      "0.14751495",
      "0.26620847",
      "0.5863901",
      "0.47668162",
      "0.7079725",
      "0.85661983",
      "0.7934463",
      "0.26620847",
      "0.6439257",
      "0.69308877",
      "0.7657704",
      "0.8030518",
      "0.47668162",
      "0.7677983",
      "0.47668162",
      "0.74369544",
      "0.80899525",
      "0.7546583",
      "0.47668162",
      "0.72192377",
      "0.14751495",
      "0.7119351",
      "0.47668162",
      "0.7398199",
      "0.47668162",
      "0.7077153",
      "0.7597803",
      "0.26620847",
      "0.7932615",
      "0.8460308",
      "0.26620847",
      "0.789891",
      "0.47668162",
      "0.5418394",
      "0.26620847",
      "0.47668162",
      "0.7916772",
      "0.841515",
      "0.0507964",
      "0.5948315",
      "0.7293024",
      "0.47668162",
      "0.47668162",
      "0.47668162",
      "0.7083833",
      "0.8514819",
      "0.7436196",
      "0.47668162",
      "0.47668162",
      "0.7465417",
      "0.8460852",
      "0.6902462",
      "0.26620847",
      "0.7935714",
      "0.26620847",
      "0.26620847",
      "0.022340713",
      "0.47668162",
      "0.26620847",
      "0.74853176",
      "0.47668162",
      "0.0219706",
      "0.6081937",
      "0.73778266",
      "0.43566808",
      "0.47668162",
      "0.47668162",
      "0.47668162",
      "0.47668162"
    ]
  },
  {
    "Title": "Cem Anos de Choro",
    "Time_signature": "2/4",
    "Part": "A",
    "Key": "E- major",
    "Generated": [
      "E-5-0.25",
      "C5-0.25",
      "G4-0.25",
      "E-4-0.25",
      "D4-0.25",
      "C4-0.5",
      "B-4-0.25",
      "B-4-0.25",
      "A-4-0.25",
      "B-4-0.25",
      "A-4-0.25",
      "B-4-0.25",
      "A-4-0.25",
      "A-4-0.5",
      "E-5-0.25",
      "A-4-0.5",
      "B-4-0.25",
      "B-4-0.5",
      "C5-0.25",
      "D4-1.0",
      "A4-0.25",
      "D4-1.0",
      "B-4-0.25",
      "D4-1.0",
      "B-4-0.25",
      "B-4-0.25",
      "B-4-0.25",
      "B-4-0.25",
      "C5-0.25",
      "C4-0.5",
      "B-4-0.25",
      "C5-0.25",
      "E-5-0.25",
      "B-4-0.25",
      "B-4-0.25",
      "B-4-0.25",
      "B-4-0.25",
      "C5-0.25",
      "B-4-0.25",
      "C5-0.25",
      "B-4-0.25",
      "C5-0.25",
      "B-4-0.25",
      "B-4-0.5",
      "B-4-0.25",
      "G4-0.25",
      "E-4-0.25",
      "B-4-0.25",
      "A-4-0.25",
      "B-4-0.25",
      "A-4-0.25",
      "B-4-0.25",
      "B-4-0.25",
      "A-4-0.25",
      "A-4-0.25",
      "B-4-0.25",
      "C5-0.25",
      "E-5-0.25",
      "B-4-0.25",
      "B-4-0.25",
      "G4-0.25",
      "B-4-0.25",
      "A-4-0.25",
      "A-4-0.25",
      "B-4-0.25",
      "A-4-0.25",
      "B-4-0.25",
      "B-4-0.25",
      "B-4-0.25",
      "A-4-0.25",
      "B-4-0.25",
      "A-4-0.25",
      "B4-0.25",
      "B-4-0.25",
      "C5-0.25",
      "B-4-0.25",
      "B-4-0.25",
      "E-4-0.25",
      "A-4-0.25",
      "A-4-0.25",
      "D4-0.25",
      "E-5-0.25",
      "A-4-0.25",
      "G4-0.25",
      "B-4-0.25",
      "B-4-0.25",
      "A-4-0.25",
      "B-4-0.5",
      "C5-0.25",
      "A-4-0.25",
      "B-4-0.25",
      "A4-0.25",
      "A-4-0.25",
      "B-4-0.25",
      "D4-0.25",
      "A-4-0.25",
      "B-4-0.5",
      "B-4-0.25",
      "A-4-0.25",
      "B-4-0.25",
      "B-4-0.25",
      "A-4-0.25",
      "B4-0.25",
      "A-4-0.25",
      "C4-0.5",
      "B-4-0.25",
      "A-4-0.25",
      "B-4-0.25",
      "B-4-0.25",
      "D5-0.25",
      "A-4-0.25",
      "B-4-0.25",
      "A-4-0.25",
      "B-4-0.25",
      "A-4-0.25",
      "B-4-0.25",
      "C5-0.25",
      "B-4-0.25",
      "A-4-0.25",
      "D4-0.25",
      "E-4-0.25",
      "B-4-0.25",
      "B-4-0.25",
      "B4-0.25",
      "B-4-0.5"
    ],
    "Original": [
      "E-5-0.25",
      "C5-0.25",
      "G4-0.25",
      "E-4-0.25",
      "D4-0.25",
      "C4-0.5",
      "B-4-0.25",
      "B-4-0.25",
      "A-4-0.25",
      "B-4-0.25",
      "A-4-0.25",
      "B-4-0.25",
      "A-4-0.25",
      "A-4-0.5",
      "A-4-0.25",
      "G4-0.25",
      "F#4-0.25",
      "G4-0.25",
      "D5-0.25",
      "A-4-0.5",
      "G4-0.25",
      "G4-0.5",
      "G4-0.25",
      "A4-0.25",
      "B4-0.25",
      "C5-0.25",
      "D5-0.25",
      "E-5-0.25",
      "C5-0.25",
      "G4-0.25",
      "E-4-0.25",
      "D4-0.25",
      "C4-0.5",
      "B-4-0.25",
      "B-4-0.25",
      "D4-0.5",
      "G4-0.25",
      "B-4-0.25",
      "C5-0.25",
      "B4-0.25",
      "B-4-0.25",
      "B-4-0.25",
      "A4-0.25",
      "G#4-0.25",
      "A4-0.25",
      "D5-0.5",
      "C5-0.25",
      "C5-0.25",
      "C5-0.25",
      "B4-0.5",
      "G4-0.25",
      "A4-0.25",
      "B4-0.25",
      "C5-0.25",
      "D5-0.25",
      "E-5-0.25",
      "C5-0.25",
      "G4-0.25",
      "E-4-0.25",
      "D4-0.25",
      "C4-0.5",
      "B-4-0.25",
      "B-4-0.25",
      "A-4-0.25",
      "B-4-0.25",
      "A-4-0.25",
      "B-4-0.25",
      "A-4-0.25",
      "A-4-0.5",
      "A-4-0.25",
      "G4-0.25",
      "F#4-0.25",
      "G4-0.25",
      "D5-0.25",
      "G4-0.5",
      "A-4-0.25",
      "A-4-0.25",
      "G4-0.5",
      "E4-0.25",
      "G4-0.25",
      "B-4-0.25",
      "D-5-0.25",
      "C5-0.5",
      "F#4-0.25",
      "F#4-0.25",
      "A4-0.25",
      "C5-0.25",
      "E-5-0.25",
      "D5-1.0",
      "G4-0.25",
      "B4-0.25",
      "D5-0.25",
      "F5-0.25",
      "E-5-0.25",
      "C5-0.25",
      "G4-0.25",
      "E-4-0.25",
      "D4-0.25",
      "E-4-0.25",
      "F4-0.25",
      "G4-0.25",
      "C4-0.5",
      "rest-0.25",
      "G4-0.25",
      "A4-0.25",
      "B4-0.25",
      "C5-0.25",
      "D5-0.25"
    ],
    "Proba": [
      "1",
      "1",
      "1",
      "1",
      "1",
      "1",
      "1",
      "1",
      "1",
      "1",
      "1",
      "1",
      "1",
      "1",
      "0.011892353",
      "0.5902819",
      "0.645442",
      "0.043257657",
      "0.6570431",
      "0.011041987",
      "0.032169014",
      "0.623855",
      "0.1764963",
      "0.17903365",
      "0.645442",
      "0.645442",
      "0.645442",
      "0.645442",
      "0.048725955",
      "0.06587626",
      "0.645442",
      "0.6840179",
      "0.6467794",
      "0.645442",
      "0.645442",
      "0.645442",
      "0.645442",
      "0.69018275",
      "0.6572311",
      "0.613007",
      "0.645442",
      "0.5864525",
      "0.645442",
      "0.058374222",
      "0.645442",
      "0.738824",
      "0.5945146",
      "0.645442",
      "0.12940769",
      "0.65301305",
      "0.19595648",
      "0.645442",
      "0.006103738",
      "0.34325966",
      "0.12940769",
      "0.645442",
      "0.7500708",
      "0.5937178",
      "0.645442",
      "0.645442",
      "0.04465594",
      "0.645442",
      "0.11856004",
      "0.12940769",
      "0.645442",
      "0.7592156",
      "0.80894405",
      "0.645442",
      "0.645442",
      "0.43811703",
      "0.7300095",
      "0.6581977",
      "0.02915712",
      "0.645442",
      "0.3632822",
      "0.645442",
      "0.645442",
      "0.03649872",
      "0.6006184",
      "0.12940769",
      "0.016772185",
      "0.011892353",
      "0.6739419",
      "0.029984953",
      "0.645442",
      "0.645442",
      "0.80436766",
      "0.058374222",
      "0.048725955",
      "0.7662295",
      "0.7443916",
      "0.024447814",
      "0.22178979",
      "0.6858489",
      "0.016772185",
      "0.5529952",
      "0.058374222",
      "0.645442",
      "0.6840637",
      "0.645442",
      "0.645442",
      "0.12940769",
      "0.02915712",
      "0.679453",
      "0.04438101",
      "0.645442",
      "0.7619822",
      "0.7905655",
      "0.645442",
      "0.015356246",
      "0.12940769",
      "0.645442",
      "0.4899605",
      "0.645442",
      "0.12940769",
      "0.645442",
      "0.02035503",
      "0.645442",
      "0.60376847",
      "0.016772185",
      "0.082796164",
      "0.645442",
      "0.645442",
      "0.02915712",
      "0.058374222"
    ]
  },
  {
    "Title": "CHORINHO NA PRAIA",
    "Time_signature": "2/4",
    "Part": "A",
    "Key": "F major",
    "Generated": [
      "B-5-0.25",
      "A5-0.5",
      "E5-0.25",
      "G5-0.25",
      "F5-0.25",
      "C#5-0.25",
      "E5-0.25",
      "E5-0.25",
      "D5-0.5",
      "B-4-0.25",
      "G4-0.25",
      "F4-0.25",
      "E4-0.25",
      "A4-0.25",
      "C#5-0.25",
      "D5-0.25",
      "A5-0.25",
      "G5-0.25",
      "D5-0.25",
      "E5-0.25",
      "A5-0.5",
      "G5-0.25",
      "A5-0.25",
      "A5-0.5",
      "A5-0.25",
      "A5-0.25",
      "A5-0.5",
      "A5-0.25",
      "A5-0.25",
      "B-5-0.25",
      "A5-0.25",
      "A5-0.25",
      "A5-0.5",
      "A5-0.25",
      "A5-0.25",
      "G5-0.25",
      "F5-0.25",
      "B-5-0.25",
      "A5-0.5",
      "A5-0.25",
      "A5-0.25",
      "A-5-0.25",
      "B-5-0.25",
      "A5-0.5",
      "B-5-0.25",
      "A5-0.25",
      "A5-0.25",
      "F5-0.25",
      "A5-0.25",
      "A5-0.5",
      "G5-0.5",
      "A5-0.5",
      "A5-0.25",
      "A5-0.5",
      "A5-0.5",
      "A5-0.25",
      "B-5-0.25",
      "A5-0.5",
      "G#5-0.25",
      "A5-0.25",
      "G#5-1.0",
      "A5-0.25",
      "A5-0.5",
      "A5-0.25",
      "A5-0.25",
      "A5-0.5",
      "A5-0.25",
      "A5-0.25",
      "C6-0.25",
      "A5-0.25",
      "A5-0.5",
      "A5-0.25",
      "B-5-0.25",
      "A5-0.5",
      "B-5-0.25",
      "A5-0.25",
      "A5-0.5",
      "E5-0.25",
      "A5-0.5",
      "A5-0.25",
      "A5-0.5",
      "A5-0.25",
      "A5-0.25",
      "A5-0.5",
      "A5-0.25",
      "B-5-0.25",
      "A5-0.5",
      "B-5-0.25",
      "A5-0.25",
      "D5-0.25",
      "A5-0.25",
      "A5-0.25",
      "B-5-0.25",
      "A5-0.25",
      "G5-0.25",
      "A5-0.5",
      "A5-0.25",
      "A5-0.25",
      "A5-0.5",
      "B-5-0.25",
      "A5-0.25",
      "A5-0.5",
      "E5-0.25",
      "B-5-0.5",
      "A5-0.5",
      "A5-0.25",
      "A5-0.5",
      "A5-0.25",
      "A5-0.25",
      "B-5-0.25",
      "A5-0.5"
    ],
    "Original": [
      "B-5-0.25",
      "A5-0.5",
      "E5-0.25",
      "G5-0.25",
      "F5-0.25",
      "C#5-0.25",
      "E5-0.25",
      "E5-0.25",
      "D5-0.5",
      "B-4-0.25",
      "G4-0.25",
      "F4-0.25",
      "E4-0.25",
      "A4-0.25",
      "A4-1.0",
      "A4-0.25",
      "D#4-0.5",
      "E4-0.25",
      "A4-1.0",
      "A4-0.25",
      "A5-0.5",
      "G#5-0.25",
      "B-5-0.25",
      "A5-0.5",
      "E5-0.25",
      "G5-0.25",
      "F5-0.5",
      "E-5-0.25",
      "F5-0.25",
      "E5-0.5",
      "D5-0.25",
      "C5-0.25",
      "B4-0.25",
      "A4-0.25",
      "E5-0.25",
      "E5-1.0",
      "E5-0.25",
      "B-4-0.5",
      "B4-0.25",
      "E5-1.0",
      "E5-0.25",
      "A5-0.5",
      "G#5-0.25",
      "B-5-0.25",
      "A5-0.5",
      "E5-0.25",
      "G5-0.25",
      "F5-0.5",
      "C#5-0.25",
      "E5-0.25",
      "D5-0.5",
      "B-4-0.25",
      "G4-0.25",
      "F4-0.25",
      "E4-0.25",
      "A4-0.25",
      "A4-1.0",
      "A4-0.25",
      "D#4-0.5",
      "E4-0.25",
      "A4-1.0",
      "A4-0.25",
      "G#4-0.5",
      "A4-0.25",
      "E-5-0.25",
      "D5-0.5",
      "C#5-0.25",
      "D5-0.25",
      "F#5-0.25",
      "B-5-0.25",
      "A5-0.25",
      "A5-0.25",
      "G5-0.5",
      "A4-0.25",
      "B-4-0.25",
      "D5-0.25",
      "A5-0.25",
      "G5-0.25",
      "G5-0.25",
      "F5-0.5",
      "D5-0.25",
      "B4-0.25",
      "C#5-0.5",
      "A4-0.25",
      "D5-1.0",
      "D5-0.25",
      "A5-0.5",
      "G#5-0.25"
    ],
    "Proba": [
      "1",
      "1",
      "1",
      "1",
      "1",
      "1",
      "1",
      "1",
      "1",
      "1",
      "1",
      "1",
      "1",
      "1",
      "0.03292225",
      "0.0688392",
      "0.5856323",
      "0.021207275",
      "0.0688392",
      "0.7929214",
      "0.1415716",
      "0.73798895",
      "0.5856323",
      "0.1415716",
      "0.5856323",
      "0.5856323",
      "0.60323256",
      "0.5856323",
      "0.5856323",
      "0.16271824",
      "0.46648544",
      "0.5856323",
      "0.1415716",
      "0.5856323",
      "0.04743939",
      "0.64895433",
      "0.61571807",
      "0.16271824",
      "0.1415716",
      "0.62314034",
      "0.5856323",
      "0.10685643",
      "0.72432977",
      "0.76014227",
      "0.16271824",
      "0.5856323",
      "0.5856323",
      "0.6035202",
      "0.5821741",
      "0.6180089",
      "0.0039385287",
      "0.59580433",
      "0.5856323",
      "0.42983896",
      "0.1415716",
      "0.5856323",
      "0.2689754",
      "0.1415716",
      "0.019234814",
      "0.5799962",
      "0.002805237",
      "0.5856323",
      "0.6456686",
      "0.67479867",
      "0.5856323",
      "0.68506867",
      "0.5856323",
      "0.5856323",
      "0.023777442",
      "0.5856323",
      "0.67984885",
      "0.6836183",
      "0.18849696",
      "0.60776454",
      "0.5855425",
      "0.5856323",
      "0.8084791",
      "0.6618925",
      "0.6863719",
      "0.5856323",
      "0.6737704",
      "0.5856323",
      "0.5856323",
      "0.7954102",
      "0.566395",
      "0.16271824",
      "0.74176055",
      "0.65407085",
      "0.07128285",
      "0.0688392",
      "0.106505744",
      "0.5856323",
      "0.21060492",
      "0.5856323",
      "0.021207275",
      "0.74646086",
      "0.5856323",
      "0.5856323",
      "0.4905761",
      "0.7617395",
      "0.5856323",
      "0.8120331",
      "0.6823893",
      "0.0069220145",
      "0.59067094",
      "0.5856323",
      "0.7023052",
      "0.5856323",
      "0.5856323",
      "0.16271824",
      "0.71629566"
    ]
  },
  {
    "Title": "BEB\u00ca",
    "Time_signature": "2/4",
    "Part": "A",
    "Key": "C major",
    "Generated": [
      "E5-0.25",
      "F5-0.25",
      "E5-0.25",
      "F5-0.25",
      "E5-0.25",
      "F5-0.25",
      "E5-0.25",
      "F5-0.25",
      "E5-0.25",
      "F5-0.25",
      "E5-0.25",
      "F5-0.25",
      "E5-0.25",
      "F5-0.25",
      "G5-0.5",
      "G5-0.25",
      "F5-0.25",
      "F5-0.25",
      "E5-0.25",
      "F5-0.25",
      "E5-0.25",
      "F5-0.25",
      "E5-0.25",
      "F5-0.25",
      "F5-0.25",
      "E5-0.25",
      "F5-0.25",
      "C6-0.25",
      "F5-0.25",
      "F5-0.25",
      "F5-0.25",
      "F5-0.25",
      "F5-0.25",
      "E5-0.25",
      "F5-0.25",
      "rest-0.25",
      "G5-0.25",
      "F5-0.25",
      "G5-0.5",
      "F5-0.25",
      "E5-0.25",
      "F5-0.25",
      "E5-0.25",
      "F5-0.25",
      "F5-0.25",
      "D5-0.5",
      "F5-0.25",
      "C6-0.25",
      "F5-0.25",
      "F5-0.25",
      "F5-0.25",
      "E5-0.25",
      "E-5-0.25",
      "F5-0.25",
      "F5-0.25",
      "C6-0.25",
      "F5-0.25",
      "D5-0.5",
      "D#5-0.25",
      "E5-0.25",
      "F5-0.25",
      "F5-0.25",
      "F5-0.25",
      "F5-0.25",
      "F5-0.25",
      "E5-0.25",
      "F5-0.25",
      "G5-0.5",
      "F5-0.25",
      "B5-0.25",
      "F5-0.25",
      "rest-0.25",
      "G5-0.25",
      "G5-0.25",
      "B-5-0.25",
      "C6-0.25",
      "E5-0.25",
      "F5-0.25",
      "F5-0.25",
      "E5-0.25",
      "F5-0.25",
      "E5-0.25",
      "G-5-0.25",
      "F5-0.25",
      "E5-0.25",
      "F5-0.25",
      "B-5-0.25",
      "G5-0.25",
      "C6-0.25",
      "F5-0.25",
      "E-5-0.25",
      "G5-0.25",
      "F5-0.25",
      "G5-0.25",
      "F5-0.25",
      "F5-0.25",
      "C6-0.25",
      "F5-0.25",
      "G5-0.25",
      "F5-0.25",
      "F5-0.25",
      "F5-0.25",
      "E5-0.25",
      "F5-0.25",
      "rest-0.25",
      "F5-0.25",
      "rest-0.25",
      "F5-0.25",
      "G5-0.25",
      "F5-0.25",
      "C6-0.25",
      "G5-0.25",
      "F5-0.25",
      "F5-0.25",
      "F5-0.25",
      "F5-0.25",
      "F5-0.25",
      "F5-0.25",
      "E5-0.25",
      "D5-0.5",
      "F5-0.25",
      "A-5-0.25",
      "G5-0.25",
      "C6-0.25",
      "F5-0.25",
      "B-5-0.25",
      "F5-0.25",
      "F5-0.25",
      "F5-0.25",
      "C6-0.25",
      "F5-0.25",
      "F5-0.25",
      "F5-0.25",
      "E5-0.25",
      "G5-0.25",
      "F5-0.25",
      "E5-0.25",
      "C6-0.25"
    ],
    "Original": [
      "E5-0.25",
      "F5-0.25",
      "E5-0.25",
      "F5-0.25",
      "E5-0.25",
      "F5-0.25",
      "E5-0.25",
      "F5-0.25",
      "E5-0.25",
      "F5-0.25",
      "E5-0.25",
      "F5-0.25",
      "E5-0.25",
      "F5-0.25",
      "G5-0.5",
      "G5-2.0",
      "G5-2.0",
      "E5-0.25",
      "F5-0.25",
      "E5-0.25",
      "F5-0.25",
      "E5-0.25",
      "F5-0.25",
      "E5-0.25",
      "F5-0.25",
      "E5-0.25",
      "F5-0.25",
      "E5-0.25",
      "F5-0.25",
      "E5-0.25",
      "F5-0.25",
      "B5-0.5",
      "B5-2.0",
      "B5-2.0",
      "B5-0.25",
      "A5-0.25",
      "D6-0.25",
      "C6-0.25",
      "B5-0.25",
      "A5-0.25",
      "D6-0.25",
      "C6-0.25",
      "B5-0.25",
      "A5-0.25",
      "D6-0.25",
      "C6-0.25",
      "B5-0.25",
      "A5-0.25",
      "A5-0.5",
      "A5-0.25",
      "G5-0.25",
      "C6-0.25",
      "B-5-0.25",
      "A5-0.25",
      "G5-0.25",
      "C6-0.25",
      "B-5-0.25",
      "A5-0.25",
      "G5-0.25",
      "C6-0.25",
      "B-5-0.25",
      "A5-0.25",
      "G5-0.25",
      "G5-0.5",
      "G5-0.25",
      "F5-0.25",
      "B-5-0.25",
      "A-5-0.25",
      "G5-0.25",
      "F5-0.25",
      "B-5-0.25",
      "A-5-0.25",
      "G5-0.25",
      "F5-0.25",
      "B-5-0.25",
      "A-5-0.25",
      "G5-0.25",
      "F5-0.25",
      "F5-0.5",
      "F5-2.0",
      "E5-2.0"
    ],
    "Proba": [
      "1",
      "1",
      "1",
      "1",
      "1",
      "1",
      "1",
      "1",
      "1",
      "1",
      "1",
      "1",
      "1",
      "1",
      "1",
      "0.1283514",
      "0.6267488",
      "0.6267488",
      "0.818585",
      "0.6267488",
      "0.7880087",
      "0.76074106",
      "0.7848728",
      "0.792854",
      "0.6267488",
      "0.8083377",
      "0.6267488",
      "0.085818656",
      "0.6267488",
      "0.32635754",
      "0.7023835",
      "0.46506006",
      "0.16561939",
      "0.76271296",
      "0.83091253",
      "0.012241902",
      "0.1283514",
      "0.6267488",
      "0.60997266",
      "0.8242292",
      "0.76237315",
      "0.6267488",
      "0.83194584",
      "0.816888",
      "0.6267488",
      "0.011980482",
      "0.6267488",
      "0.085818656",
      "0.6267488",
      "0.6267488",
      "0.6267488",
      "0.8050695",
      "0.015053752",
      "0.6267488",
      "0.6267488",
      "0.085818656",
      "0.6267488",
      "0.014000312",
      "0.007835021",
      "0.73800576",
      "0.6267488",
      "0.6267488",
      "0.6267488",
      "0.6267488",
      "0.6267488",
      "0.79873264",
      "0.8286796",
      "0.037559178",
      "0.8162928",
      "0.024667136",
      "0.6267488",
      "0.012481362",
      "0.1283514",
      "0.1283514",
      "0.036026422",
      "0.085818656",
      "0.495824",
      "0.6267488",
      "0.6267488",
      "0.7584066",
      "0.8182976",
      "0.6406902",
      "0.021457223",
      "0.6267488",
      "0.75698817",
      "0.6267488",
      "0.036026422",
      "0.1283514",
      "0.085818656",
      "0.6267488",
      "0.01185711",
      "0.1283514",
      "0.6267488",
      "0.1283514",
      "0.7931707",
      "0.6267488",
      "0.085818656",
      "0.6267488",
      "0.1283514",
      "0.6267488",
      "0.6267488",
      "0.6267488",
      "0.82450014",
      "0.6267488",
      "0.03089186",
      "0.6267488",
      "0.03089186",
      "0.80077463",
      "0.1283514",
      "0.78796256",
      "0.085818656",
      "0.6570181",
      "0.6267488",
      "0.6267488",
      "0.6267488",
      "0.6267488",
      "0.0955105",
      "0.13216566",
      "0.7273477",
      "0.014708096",
      "0.7901151",
      "0.014528256",
      "0.1283514",
      "0.085818656",
      "0.6267488",
      "0.036026422",
      "0.812785",
      "0.6267488",
      "0.6267488",
      "0.085818656",
      "0.6267488",
      "0.6267488",
      "0.09466398",
      "0.7821665",
      "0.1283514",
      "0.6267488",
      "0.72791195",
      "0.085818656"
    ]
  },
  {
    "Title": "Mistura e Manda",
    "Time_signature": "2/4",
    "Part": "A",
    "Key": "D major",
    "Generated": [
      "F#5-0.25",
      "E5-0.5",
      "D#5-0.25",
      "E5-0.25",
      "A5-0.5",
      "A5-0.25",
      "A5-1.0",
      "A5-0.25",
      "F#5-0.25",
      "E5-0.25",
      "D5-0.25",
      "E5-0.25",
      "F#5-0.25",
      "E5-0.25",
      "B#4-0.25",
      "E5-0.25",
      "D5-0.25",
      "E5-0.25",
      "C#5-0.25",
      "E5-0.25",
      "E5-0.25",
      "D5-0.25",
      "G5-0.25",
      "E5-0.25",
      "E5-0.25",
      "D#5-0.25",
      "E5-0.25",
      "B4-0.25",
      "E5-0.25",
      "G5-0.25",
      "E5-0.25",
      "E5-0.5",
      "B-4-0.25",
      "E5-0.25",
      "D5-0.25",
      "E5-0.25",
      "B4-0.25",
      "B4-2.0",
      "E5-0.25",
      "G5-0.25",
      "F#5-0.25",
      "F#5-0.25",
      "E5-0.5",
      "D4-0.25",
      "D#5-0.25",
      "D5-0.25",
      "G5-0.25",
      "E5-0.25",
      "G5-0.25",
      "D5-0.25",
      "E5-0.25",
      "E5-0.25",
      "D5-0.25",
      "F#5-0.25",
      "F#5-0.25",
      "E5-0.25",
      "E5-0.25",
      "D5-0.25",
      "F#5-0.25",
      "E5-0.25",
      "E5-0.25",
      "G5-0.25",
      "E5-0.25",
      "D5-0.25",
      "B-4-0.25",
      "D5-0.25",
      "E5-0.25",
      "D5-0.25",
      "E5-0.25",
      "D5-0.25",
      "A4-0.25",
      "B-4-0.25",
      "E5-0.25",
      "E5-0.25",
      "E5-0.5",
      "F#5-0.25",
      "E5-0.25",
      "E5-0.25",
      "E5-0.25",
      "A5-0.5",
      "A5-0.25",
      "D5-0.25",
      "E5-0.25",
      "B-4-0.25",
      "F#5-0.25",
      "E5-0.25",
      "D5-0.25",
      "E5-0.25",
      "D5-0.25",
      "E5-0.25",
      "C#5-0.25",
      "E5-0.25",
      "E5-0.25",
      "D5-0.25",
      "B-4-0.25",
      "E5-0.25",
      "E5-0.25",
      "F#5-0.25",
      "E5-0.25",
      "E5-0.25",
      "D#5-0.25",
      "B-4-0.25",
      "E5-0.25",
      "F5-0.125",
      "E5-0.25",
      "E5-0.25",
      "E5-0.25",
      "F#5-0.25",
      "D5-0.25",
      "G5-0.5",
      "D5-0.25",
      "E5-0.25",
      "E5-0.25",
      "E5-0.25",
      "D#5-0.25",
      "E5-0.25",
      "D#5-0.25",
      "C#5-0.25",
      "B-4-0.25",
      "E5-0.25",
      "D#5-0.25",
      "E5-0.25",
      "A5-0.5",
      "D5-0.25",
      "E5-0.25",
      "F#5-0.25",
      "E5-0.125"
    ],
    "Original": [
      "F#5-0.25",
      "E5-0.5",
      "D#5-0.25",
      "E5-0.25",
      "A5-0.5",
      "A5-0.25",
      "A5-1.0",
      "A5-0.25",
      "F#5-0.25",
      "E5-0.25",
      "D5-0.25",
      "C#5-0.25",
      "A#3-0.25",
      "C#4-0.25",
      "E4-0.25",
      "G4-0.25",
      "A#4-0.25",
      "C#5-0.25",
      "E5-0.25",
      "E5-0.5",
      "D5-0.25",
      "D5-0.25",
      "C#5-0.25",
      "D5-0.25",
      "E5-0.25",
      "F5-0.25",
      "D5-0.25",
      "B4-0.25",
      "G#4-0.25",
      "F4-0.25",
      "D4-0.25",
      "B3-0.25",
      "G#3-0.25",
      "B4-0.5",
      "A4-0.25",
      "A4-0.25",
      "C#4-0.25",
      "D4-0.25",
      "D#4-0.25",
      "E4-0.25",
      "F#4-0.25",
      "G#4-0.25",
      "A4-0.25",
      "A#4-0.25",
      "B4-0.25",
      "C#5-0.25",
      "B4-0.25",
      "E5-0.5",
      "rest-0.25",
      "F#5-0.25",
      "F#5-0.25",
      "C5-0.25",
      "D5-0.25",
      "F#5-0.25",
      "G5-0.25",
      "B4-0.25",
      "D5-0.25",
      "G5-0.25",
      "E5-0.25",
      "B-4-0.25",
      "C5-0.25",
      "E5-0.25",
      "F#5-0.25",
      "A4-0.25",
      "C5-0.25",
      "F#5-0.25",
      "D5-0.25",
      "A-4-0.25",
      "B-4-0.25",
      "D5-0.25",
      "E-5-0.25",
      "G4-0.25",
      "B-4-0.25",
      "E-5-0.25",
      "C#5-0.25",
      "G4-0.25",
      "A4-0.25",
      "C#5-0.25",
      "D5-0.25",
      "F#4-0.25",
      "A4-0.25",
      "D5-0.25",
      "E5-0.25",
      "D5-0.25",
      "F5-0.5",
      "F5-0.25",
      "D5-0.25",
      "B4-0.25",
      "G#4-0.25",
      "F4-0.25",
      "D4-0.25",
      "B3-0.25",
      "G#3-0.25",
      "B4-0.25",
      "A4-0.5",
      "F#5-0.25",
      "F#5-0.25",
      "D5-0.25",
      "B4-0.25",
      "A4-0.25",
      "G#4-0.25",
      "F#5-0.5",
      "E5-0.25",
      "G4-0.25",
      "F#5-0.25",
      "E5-0.25",
      "D5-0.25",
      "D5-0.25",
      "B4-0.25",
      "A4-0.25",
      "F#4-0.25",
      "E4-0.25",
      "F#5-0.25",
      "G5-0.25",
      "D#5-0.25"
    ],
    "Proba": [
      "1",
      "1",
      "1",
      "1",
      "1",
      "1",
      "1",
      "1",
      "1",
      "1",
      "1",
      "0.59661514",
      "0.14271471",
      "0.59661514",
      "0.011002243",
      "0.59661514",
      "0.08771089",
      "0.59661514",
      "0.026130103",
      "0.59661514",
      "0.59661514",
      "0.08771089",
      "0.01684545",
      "0.59661514",
      "0.59661514",
      "0.6010061",
      "0.73112696",
      "0.009795869",
      "0.713366",
      "0.47669196",
      "0.59661514",
      "0.33901516",
      "0.09634024",
      "0.59661514",
      "0.08771089",
      "0.7805536",
      "0.009795869",
      "0.012143579",
      "0.59661514",
      "0.039915796",
      "0.036777783",
      "0.14271471",
      "0.11467328",
      "0.0077657234",
      "0.6115934",
      "0.08771089",
      "0.020478478",
      "0.27523714",
      "0.58326316",
      "0.08771089",
      "0.59661514",
      "0.59661514",
      "0.5946556",
      "0.14271471",
      "0.14271471",
      "0.59661514",
      "0.59661514",
      "0.08771089",
      "0.14271471",
      "0.773372",
      "0.59661514",
      "0.66413194",
      "0.59661514",
      "0.08771089",
      "0.09634024",
      "0.08771089",
      "0.59661514",
      "0.55750597",
      "0.7630297",
      "0.6371856",
      "0.016232798",
      "0.09634024",
      "0.7488026",
      "0.59661514",
      "0.5993352",
      "0.780621",
      "0.59661514",
      "0.59661514",
      "0.59661514",
      "0.67232394",
      "0.04093374",
      "0.68048847",
      "0.59661514",
      "0.09634024",
      "0.14271471",
      "0.7714508",
      "0.345519",
      "0.7846214",
      "0.7471732",
      "0.7806321",
      "0.026130103",
      "0.59661514",
      "0.59661514",
      "0.08771089",
      "0.09634024",
      "0.60523486",
      "0.59661514",
      "0.14271471",
      "0.7487457",
      "0.59661514",
      "0.5986037",
      "0.09634024",
      "0.69715446",
      "0.025482962",
      "0.79135084",
      "0.59661514",
      "0.59661514",
      "0.6968179",
      "0.15046859",
      "0.019343816",
      "0.6283741",
      "0.7936871",
      "0.59661514",
      "0.59661514",
      "0.17733186",
      "0.7669445",
      "0.61262864",
      "0.026130103",
      "0.09634024",
      "0.59661514",
      "0.67345226",
      "0.59661514",
      "0.029974617",
      "0.06970665",
      "0.7984432",
      "0.14271471",
      "0.73346883"
    ]
  }
]